<?xml version="1.0"?>
<package>
    <name>addthis_sharingtool</name>
    <version>2.0.1</version>
    <stability>stable</stability>
    <license uri="http://www.apache.org/licenses/LICENSE-2.0">Apache</license>
    <channel>community</channel>
    <extends/>
    <summary>AddThis makes it easy for any visitor to share your content to over 350 services. Developed by AddThis.</summary>
    <description>Get more traffic back to your site by installing the AddThis Magento Extension! With AddThis, your users can promote your content by sharing to 350 of the most popular social networking and bookmarking sites (like Facebook, Twitter, Google +1, Pinterest and LinkedIn). AddThis is used on over 12 million domains, seen by over 1.2 billion users a month, quick to load and recognized all over the web. Optionally, sign up for a free AddThis.com account to see how your visitors are sharing your content: which services they're using for sharing (including their browser address bar), which content is shared the most, what text of interest they're copying from your site, and more. Analytics are available in real time. Developed in-house by AddThis.com.&#xD;
Now we have also incorporated SmartLayers in this extension to make your site smarter. Increase traffic, engagement and revenue by instantly showing the right social tools and content to every visitor. It's one piece of code, mobile-ready and free! </description>
    <notes>* Implemented SmartLayers&#xD;
* Added new section for managing Profile ID</notes>
    <authors><author><name>AddThis</name><user>plugins_addthis</user><email>plugins@addthis.com</email></author></authors>
    <date>2013-11-11</date>
    <time>13:44:13</time>
    <contents><target name="mageetc"><dir name="modules"><file name="AddThis_Sharingtool.xml" hash="07328e21767411eac7403ccc78bb2710"/></dir></target><target name="magecommunity"><dir name="AddThis"><dir name="PluginsGeneral"><dir name="Helper"><file name="Data.php" hash="c2229d706cafec9f49fd9c88f1b73759"/></dir><dir name="etc"><file name="config.xml" hash="ae6e1db765bc79317cf707e158da2a40"/><file name="system.xml" hash="1912ba67e3b0847ff479aa0006dd0a68"/></dir></dir><dir name="SharingTool"><dir name="Block"><file name="Share.php" hash="010ceb12934ef3ae39b348495f29c966"/></dir><dir name="Helper"><file name="Data.php" hash="d78c69dd706b97e39ef4c856c3c9d938"/></dir><dir name="Model"><file name="Observer.php" hash="9a322fef544361af90a8cf5d944f67ac"/><dir name="Source"><file name="Buttons.php" hash="36747ed838586886dd8d7c5412db6183"/><file name="Languages.php" hash="c2527e95cfc81de57230fc41413da30e"/><file name="Menuhover.php" hash="403712eca479672709c8d400c3e8fb71"/><file name="Menuversions.php" hash="7c68a011a001b44f202f5774c32880ba"/><file name="Uihover.php" hash="619d9e5d96f15da367af4096ab448f5a"/></dir></dir><dir name="etc"><file name="config.xml" hash="0229919cfd8c17bf9ca572d449d58d81"/><file name="system.xml" hash="4a91cc8f41a1fca85269f9aad31c77de"/></dir></dir><dir name="SmartLayers"><dir name="Block"><file name="Layer.php" hash="ff9c97fee5c9d729da2a251a776f1cc6"/></dir><dir name="Helper"><file name="Data.php" hash="5e7c2293a8b4211614284c73bd67b982"/></dir><dir name="Model"><file name="Observer.php" hash="77a1a1a8b90401f70b0a7f3cd7b44c3a"/><dir name="Source"><file name="Sharebuttoncount.php" hash="bc069484c899b8a6d7ce7aa2ac190825"/><file name="Shareposition.php" hash="5423eb0a41d7ffa37ddc7731527f1787"/><file name="Theme.php" hash="7dbedb75131d4f2166a5f967c607b877"/></dir></dir><dir name="etc"><file name="config.xml" hash="85d64e8cb9c612492ff6199b3d05b286"/><file name="system.xml" hash="84ea3c15dfccedb192688dd8936d2fab"/></dir></dir></dir></target><target name="magedesign"><dir name="frontend"><dir name="default"><dir name="default"><dir name="layout"><file name="smartlayers.xml" hash="d7446606b33be1dc05f26ee960615044"/><file name="sharingtool.xml" hash="c3408376e653249f8c26c64a65190877"/></dir><dir name="template"><dir name="addthis"><dir name="sharingtool"><file name="share.phtml" hash="9bb3dda42fae0b71b366d0eaa33fb1c7"/></dir><dir name="smartlayers"><file name="smartlayers.phtml" hash="b743cd2866a700b6c4ec6e96969389eb"/></dir></dir></dir></dir></dir></dir></target></contents>
    <compatible/>
    <dependencies><required><php><min>5.2.0</min><max>6.0.0</max></php></required></dependencies>
</package>
